rs.py
recipescrapperminecraftpytjun-0.0.1.dist-info/licenses/LICENSE.txt
recipescrapperminecraftpytjun-0.0.1.dist-info/METADATA
recipescrapperminecraftpytjun-0.0.1.dist-info/WHEEL
recipescrapperminecraftpytjun-0.0.1.dist-info/top_level.txt
recipescrapperminecraftpytjun-0.0.1.dist-info/RECORD
