Metadata-Version: 2.4
Name: recipescrapperminecraftpytjun
Version: 0.0.1
Summary: Package for scrapping recipes minecraft
Author-email: Vitalii <vitalii.movchan.mkb.2019@lpnu.ua>
License: MIT License
Classifier: Programming Language :: Python :: 3
Classifier: Operating System :: OS Independent
Requires-Python: >=3.10
License-File: LICENSE.txt
Requires-Dist: requests>=2.32.3
Requires-Dist: beautifulsoup4>=4.13.4
Requires-Dist: pandas>=2.2.3
Dynamic: license-file
